sqtdiat/__init__.py
sqtdiat/qops.py
sqtdiat/two_q_tomo.py
sqtdiat-0.0.0.3.22.dist-info/LICENSE.txt
sqtdiat-0.0.0.3.22.dist-info/METADATA
sqtdiat-0.0.0.3.22.dist-info/WHEEL
sqtdiat-0.0.0.3.22.dist-info/top_level.txt
sqtdiat-0.0.0.3.22.dist-info/RECORD
