Metadata-Version: 2.1
Name: sqtdiat
Version: 0.0.0.3.22
Summary: Contains the code to perform certain mathematical operations involved in quantum computing.
Home-page: 
Author: Umesh, Ashish, Pavan, Aparajith
Author-email: p.b.ashish786@gmail.com
Classifier: Programming Language :: Python :: 3
Classifier: License :: OSI Approved :: MIT License
Classifier: Operating System :: OS Independent
Requires-Python: >=3.6
License-File: LICENSE.txt
